{
    "cosignerData": {
        "id": 157767,
        "cosignerId": "5838d976-368b-11ed-9e2d-0aa99d118edc",
        "firstName": "Testinggg2",
        "middleName": "",
        "lastName": "",
        "cosignerName": "Testinggg2",
        "dob": "",
        "mobile": "2345678909",
        "gender": "",
        "landline": "",
        "cosignerEmail": "",
        "netMonthlyIncome": "",
        "occupation": "",
        "relation": "",
        "relationProof": "",
        "citizeship": "",
        "hlMtInstallment": "",
        "panNo": "",
        "currentCountry": "",
        "currentState": "",
        "currentCity": "",
        "permanentCountry": "",
        "permanentState": "",
        "permanentCity": "",
        "employmentStatusId": "",
        "consent": "",
        "otpVerifiedAt": "",
        "olMtInstallment": "",
        "banking": [],
        "work": [],
        "address": [],
        "advance": []
    },
    "lead": {
        "id": 202829,
        "leadId": "LEAD-202829",
        "borrowerId": "6f6c96da-1749-11ed-8e6c-0aa99d118edc",
        "takeIn": "",
        "priority": "0",
        "assignee": 1019,
        "leadType": "",
        "emailId": "priya.raut@credenc.com",
        "firstName": "priya",
        "lastName": "testinHHHHH",
        "mobile": "6333333377",
        "status": 31,
        "updatedBy": 741,
        "followuptime": "",
        "modified": {
            "date": "2022-09-17 17:37:24.000000",
            "timezone_type": 3,
            "timezone": "Asia/Kolkata"
        },
        "created": {
            "date": "2022-08-09 00:09:28.000000",
            "timezone_type": 3,
            "timezone": "Asia/Kolkata"
        },
        "leadSubType": "41",
        "closedStatement": "",
        "creditNote": "",
        "creditStatus": "",
        "pendingDocList": "",
        "productType": "3",
        "leadlogs": [
            {
                "log": "",
                "name": "Priya Raut",
                "createdTime": "10-Aug-2022 04:18 PM"
            },
            {
                "log": "",
                "name": "Priya Raut",
                "createdTime": "10-Aug-2022 04:18 PM"
            },
            {
                "log": "",
                "name": "Priya Raut",
                "createdTime": "09-Aug-2022 02:39 PM"
            }
        ],
        "banklogs": [],
        "creditRemarks": [],
        "callRecordings": [],
        "pdfExist": {
            "incred": {
                "path": "/var/www/html/credenc-crm/api/public/BANK_DATA/LEAD-202829/incred.pdf",
                "isGenerated": 0
            },
            "avanse": {
                "path": "/var/www/html/credenc-crm/api/public/BANK_DATA/LEAD-202829/avanse.pdf",
                "isGenerated": 0
            },
            "credila": {
                "path": "/var/www/html/credenc-crm/api/public/BANK_DATA/LEAD-202829/credila.pdf",
                "isGenerated": 0
            },
            "auxilo": {
                "path": "/var/www/html/credenc-crm/api/public/BANK_DATA/LEAD-202829/auxilo.pdf",
                "isGenerated": 0
            }
        },
        "leadBankStatus": [],
        "leadCallStatus": [
            {
                "status": "14",
                "log": ""
            },
            {
                "status": "41",
                "log": ""
            },
            {
                "status": "31",
                "log": ""
            }
        ],
        "lastremark": "",
        "bankStatus": [],
        "callstat": " =>  => ",
        "selectedStatus": 31
    },
    "consentFor": "cosigner",
    "init": "send"
}